Exercise/binary_7segment.sv
module Binary_7segment(
    input wire [3:0] in,
    output reg a, b, c, d, e, f, g
);
    always_comb begin
        case (in)
            4'b0000: {a, b, c, d, e, f, g} = 7'b1111110; // 0
            4'b0001: {a, b, c, d, e, f, g} = 7'b0110000; // 1
            4'b0010: {a, b, c, d, e, f, g} = 7'b1101101; // 2
            4'b0011: {a, b, c, d, e, f, g} = 7'b1111001; // 3
            4'b0100: {a, b, c, d, e, f, g} = 7'b0110011; // 4
            4'b0101: {a, b, c, d, e, f, g} = 7'b1011011; // 5
            4'b0110: {a, b, c, d, e, f, g} = 7'b1011111; // 6
            4'b0111: {a, b, c, d, e, f, g} = 7'b1110000; // 7
            4'b1000: {a, b, c, d, e, f, g} = 7'b1111111; // 8
            4'b1001: {a, b, c, d, e, f, g} = 7'b1111011; // 9
            4'b1010: {a, b, c, d, e, f, g} = 7'b1110111; // A
            4'b1011: {a, b, c, d, e, f, g} = 7'b0011111; // b
            4'b1100: {a, b, c, d, e, f, g} = 7'b1001110; // C
            4'b1101: {a, b, c, d, e, f, g} = 7'b0111101; // d
            4'b1110: {a, b, c, d, e, f, g} = 7'b1001111; // E
            4'b1111: {a, b, c, d, e, f, g} = 7'b1000111; // F
            default: {a, b, c, d, e, f, g} = 7'b0000000; // Default
        endcase
    end
endmodule

Exercise/binary_7segment_tb.sv
`timescale 1ns / 1ps

module Binary_7segment_tb;
  reg [3:0] bin;
  wire a,b,c,d,e,f,g;
  
  Binary_7segment dut(
    .in(bin),
    .a(a),
    .b(b),
    .c(c),
    .d(d),
    .e(e),
    .f(f),
    .g(g)
  );
  
  initial begin
    integer i;
    for(i=0;i<=15;i=i+1) begin
      bin = i;
      #10;
    end
    $finish;
  end
  
  initial begin 
    $dumpfile("binary_7segment_decoder.vcd");
    $dumpvars(0,Binary_7segment_tb);
  end
endmodule

Exercise/Exercise.sim/sim_1/behav/xsim/binary_7segment_decoder.vcd
$date
   Fri Jan 24 10:52:17 2025
$end

$version
  2024.2.0
  $dumpfile ("binary_7segment_decoder.vcd") 
$end

$timescale
  1ps
$end

$scope module Binary_7segment_tb $end
$var reg 4 ! bin [3:0] $end
$var wire 1 " a $end
$var wire 1 # b $end
$var wire 1 $ c $end
$var wire 1 % d $end
$var wire 1 & e $end
$var wire 1 ' f $end
$var wire 1 ( g $end
$scope module dut $end
$var wire 4 ) in [3:0] $end
$var reg 1 * a $end
$var reg 1 + b $end
$var reg 1 , c $end
$var reg 1 - d $end
$var reg 1 . e $end
$var reg 1 / f $end
$var reg 1 0 g $end
$upscope $end
$scope begin Block18_2 $end
$var integer 32 1 i [31:0] $end
$upscope $end
$upscope $end
$enddefinitions $end

#0
$dumpvars
b0 !
1"
1#
1$
1%
1&
1'
0(
b0 )
1*
1+
1,
1-
1.
1/
00
b0 1
$end

#10000
b1 !
0"
0%
0&
0'
b1 )
0*
0-
0.
0/
b1 1

#20000
b10 !
1"
0$
1%
1&
1(
b10 )
1*
0,
1-
1.
10
b10 1

#30000
b11 !
1$
0&
b11 )
1,
0.
b11 1

#40000
b100 !
0"
0%
1'
b100 )
0*
0-
1/
b100 1

#50000
b101 !
1"
0#
1%
b101 )
1*
0+
1-
b101 1

#60000
b110 !
1&
b110 )
1.
b110 1

#70000
b111 !
1#
0%
0&
0'
0(
b111 )
1+
0-
0.
0/
00
b111 1

#80000
b1000 !
1%
1&
1'
1(
b1000 )
1-
1.
1/
10
b1000 1

#90000
b1001 !
0&
b1001 )
0.
b1001 1

#100000
b1010 !
0%
1&
b1010 )
0-
1.
b1010 1

#110000
b1011 !
0"
0#
1%
b1011 )
0*
0+
1-
b1011 1

#120000
b1100 !
1"
0$
0(
b1100 )
1*
0,
00
b1100 1

#130000
b1101 !
0"
1#
1$
0'
1(
b1101 )
0*
1+
1,
0/
10
b1101 1

#140000
b1110 !
1"
0#
0$
1'
b1110 )
1*
0+
0,
1/
b1110 1

#150000
b1111 !
0%
b1111 )
0-
b1111 1

#160000
b10000 1
