Exercise/Exercise.srcs/sources_1/new/Binary_7segment.sv
`timescale 1ns / 1ps

module Binary_7segment(
    input wire [3:0] in,
    output a,b,c,d,e,f,g  
    );
    segment_a seg_A(in,a);
    segment_b seg_B(in,b);
    segment_c seg_C(in,c);
    segment_d seg_D(in,d);
    segment_e seg_E(in,e);
    segment_f seg_F(in,f);
    segment_g seg_G(in,g);
    //...
endmodule

module segment_a(
    input wire[3:0] in,
    output logic out
    );

    always_comb begin
        case(in)
            4'b0000 : out = 1; //0
            4'b0001 : out = 0; //1
            4'b0010 : out = 1; //2
            4'b0011 : out = 1; //3
            4'b0100 : out = 0; //4
            4'b0101 : out = 1; //5
            4'b0110 : out = 1; //6
            4'b0111 : out = 1; //7
            4'b1000 : out = 1; //8
            4'b1001 : out = 1; //9
            default : out = 0; //Defualt
        endcase
    end
endmodule

module segment_b(
    input wire[3:0] in,
    output logic out
    );

    always_comb begin
        case(in)
            4'b0000 : out = 1; //0
            4'b0001 : out = 1; //1
            4'b0010 : out = 1; //2
            4'b0011 : out = 1; //3
            4'b0100 : out = 1; //4
            4'b0101 : out = 0; //5
            4'b0110 : out = 0; //6
            4'b0111 : out = 1; //7
            4'b1000 : out = 1; //8
            4'b1001 : out = 1; //9
            default : out = 0; //Defualt
        endcase
    end
endmodule

module segment_c(
    input wire[3:0] in,
    output logic out
    );

    always_comb begin
        case(in)
            4'b0000 : out = 1; //0
            4'b0001 : out = 1; //1
            4'b0010 : out = 0; //2
            4'b0011 : out = 1; //3
            4'b0100 : out = 1; //4
            4'b0101 : out = 1; //5
            4'b0110 : out = 1; //6
            4'b0111 : out = 1; //7
            4'b1000 : out = 1; //8
            4'b1001 : out = 1; //9
            default : out = 0; //Defualt
        endcase
    end
endmodule

module segment_d(
    input wire[3:0] in,
    output logic out
    );

    always_comb begin
        case(in)
            4'b0000 : out = 1; //0
            4'b0001 : out = 0; //1
            4'b0010 : out = 1; //2
            4'b0011 : out = 1; //3
            4'b0100 : out = 0; //4
            4'b0101 : out = 1; //5
            4'b0110 : out = 1; //6
            4'b0111 : out = 0; //7
            4'b1000 : out = 1; //8
            4'b1001 : out = 1; //9
            default : out = 0; //Defualt
        endcase
    end
endmodule

module segment_e(
    input wire[3:0] in,
    output logic out
    );

    always_comb begin
        case(in)
            4'b0000 : out = 1; //0
            4'b0001 : out = 0; //1
            4'b0010 : out = 1; //2
            4'b0011 : out = 0; //3
            4'b0100 : out = 0; //4
            4'b0101 : out = 0; //5
            4'b0110 : out = 1; //6
            4'b0111 : out = 0; //7
            4'b1000 : out = 1; //8
            4'b1001 : out = 0; //9
            default : out = 0; //Defualt
        endcase
    end
endmodule

module segment_f(
    input wire[3:0] in,
    output logic out
    );

    always_comb begin
        case(in)
            4'b0000 : out = 1; //0
            4'b0001 : out = 0; //1
            4'b0010 : out = 0; //2
            4'b0011 : out = 0; //3
            4'b0100 : out = 1; //4
            4'b0101 : out = 1; //5
            4'b0110 : out = 1; //6
            4'b0111 : out = 0; //7
            4'b1000 : out = 1; //8
            4'b1001 : out = 1; //9
            default : out = 0; //Defualt
        endcase
    end
endmodule

module segment_g(
    input wire[3:0] in,
    output logic out
    );

    always_comb begin
        case(in)
            4'b0000 : out = 0; //0
            4'b0001 : out = 0; //1
            4'b0010 : out = 1; //2
            4'b0011 : out = 1; //3
            4'b0100 : out = 1; //4
            4'b0101 : out = 1; //5
            4'b0110 : out = 1; //6
            4'b0111 : out = 0; //7
            4'b1000 : out = 1; //8
            4'b1001 : out = 1; //9
            default : out = 0; //Defualt
        endcase
    end
endmodule

Exercise/binary_7segment_tb.sv
`timescale 1ns / 1ps

module Binary_7segment_tb;
  reg [3:0] bin;
  wire a,b,c,d,e,f,g;
  
  Binary_7segment dut(
    .in(bin),
    .a(a),
    .b(b),
    .c(c),
    .d(d),
    .e(e),
    .f(f),
    .g(g)
  );
  
  initial begin
    integer i;
    for(i=0;i<=15;i=i+1) begin
      bin = i;
      #10;
    end
    $finish;
  end
  
  initial begin 
    $dumpfile("binary_7segment_decoder.vcd");
    $dumpvars(0,Binary_7segment_tb);
  end
endmodule

Exercise/Exercise.sim/sim_1/behav/xsim/binary_7segment_decoder.vcd
$date
   Wed Jan 22 14:59:51 2025
$end

$version
  2024.2.0
  $dumpfile ("binary_7segment_decoder.vcd") 
$end

$timescale
  1ps
$end

$scope module Binary_7segment_tb $end
$var reg 4 ! bin [3:0] $end
$var wire 1 " a $end
$var wire 1 # b $end
$var wire 1 $ c $end
$var wire 1 % d $end
$var wire 1 & e $end
$var wire 1 ' f $end
$var wire 1 ( g $end
$scope module dut $end
$var wire 4 ) in [3:0] $end
$var wire 1 " a $end
$var wire 1 # b $end
$var wire 1 $ c $end
$var wire 1 % d $end
$var wire 1 & e $end
$var wire 1 ' f $end
$var wire 1 ( g $end
$scope module seg_A $end
$var wire 4 ) in [3:0] $end
$var reg 1 * out $end
$upscope $end
$scope module seg_B $end
$var wire 4 ) in [3:0] $end
$var reg 1 + out $end
$upscope $end
$scope module seg_C $end
$var wire 4 ) in [3:0] $end
$var reg 1 , out $end
$upscope $end
$scope module seg_D $end
$var wire 4 ) in [3:0] $end
$var reg 1 - out $end
$upscope $end
$scope module seg_E $end
$var wire 4 ) in [3:0] $end
$var reg 1 . out $end
$upscope $end
$scope module seg_F $end
$var wire 4 ) in [3:0] $end
$var reg 1 / out $end
$upscope $end
$scope module seg_G $end
$var wire 4 ) in [3:0] $end
$var reg 1 0 out $end
$upscope $end
$upscope $end
$scope begin Block18_8 $end
$var integer 32 1 i [31:0] $end
$upscope $end
$upscope $end
$enddefinitions $end

#0
$dumpvars
b0 !
1"
1#
1$
1%
1&
1'
0(
b0 )
1*
1+
1,
1-
1.
1/
00
b0 1
$end

#10000
b1 !
0"
0%
0&
0'
b1 )
0*
0-
0.
0/
b1 1

#20000
b10 !
1"
0$
1%
1&
1(
b10 )
1*
0,
1-
1.
10
b10 1

#30000
b11 !
1$
0&
b11 )
1,
0.
b11 1

#40000
b100 !
0"
0%
1'
b100 )
0*
0-
1/
b100 1

#50000
b101 !
1"
0#
1%
b101 )
1*
0+
1-
b101 1

#60000
b110 !
1&
b110 )
1.
b110 1

#70000
b111 !
1#
0%
0&
0'
0(
b111 )
1+
0-
0.
0/
00
b111 1

#80000
b1000 !
1%
1&
1'
1(
b1000 )
1-
1.
1/
10
b1000 1

#90000
b1001 !
0&
b1001 )
0.
b1001 1

#100000
b1010 1
