HW1/instruction.vh
parameter WORD_SIZE = 16;

`define ALU_ADD 4'h0 //0000
`define ALU_SUB 4'h1
`define ALU_MUL 4'h2
`define ALU_SLT 4'h3
`define ALU_AND 4'h4
`define ALU_OR 4'h5
`define ALU_XOR 4'h6
`define ALU_SHL 4'h7 
`define ALU_SHR 4'h8 //1000

vivado_project/HW1_ALU/HW1_ALU.srcs/sources_1/new/alu.sv
module alu(clk, op, in1, in2, alu_enable, out);

    `include "instruction.vh"

    input wire [3:0] op; // op code is 4 bits
    input wire [WORD_SIZE-1:0] in1, in2; // operands
    input wire clk, alu_enable; // enable and clock
    output reg [WORD_SIZE-1:0] out; // result

    always @(posedge clk) begin
        if (alu_enable) begin
            case (op)
                `ALU_ADD:
                    out <= in1 + in2;
                `ALU_SUB:
                    out <= in1 - in2;
                `ALU_MUL:
                    out <= in1 * in2;
                `ALU_SLT:
                    out <= in1 < in2;
                `ALU_AND:
                    out <= in1 & in2;
                `ALU_OR:
                    out <= in1 | in2;
                `ALU_XOR:
                    out <= in1 ^ in2;
                `ALU_SHL:
                    out <= in1 << in2;
                `ALU_SHR:
                    out <= in1 >> in2;
                default:
                    out <= {WORD_SIZE{1'bz}};
            endcase
        end
    end
endmodule

vivado_project/HW1_ALU/HW1_ALU.srcs/sim_1/new/alu_tb.sv
`timescale 1ns/1ps
module alu_tb;

    `include "instruction.vh"
    // input
    reg [3:0] op;
    reg [WORD_SIZE-1:0] expected;
    reg [WORD_SIZE-1:0] in1, in2;
    reg [(WORD_SIZE*3)+4:0] test_case [0:8];
    reg alu_enable = 1;
  
    // output
    wire [WORD_SIZE-1:0] out;

    //CLK
    reg clk = 1'b1;
    always #5 clk = !clk;

    // Instantiate the ALU module
    alu alu0 (
        .clk(clk),
        .op(op),
        .in1(in1),
        .in2(in2),
        .alu_enable(alu_enable),
        .out(out)
    );
    
    initial begin
        $readmemh("test_case.hex",test_case);
        #50;
        for (integer i = 0; i < 9; i = i + 1) begin
            #10 {op,in1,in2,expected} = test_case[i];
        end
      	#10;
        $finish; // End simulation
    end
  
    always @(negedge clk)begin
        if(alu_enable)begin
            $monitor("Time:%0t, op = %d, in1 = %d, in2 = %d, expected = %d, out = %d, ok = %d",$time,op, in1, in2, expected, out, (expected == out));
        end
    end
    initial begin
      $dumpfile("ALU.vcd");
      $dumpvars(0,alu_tb);
    end
endmodule

vivado_project/HW1_ALU/HW1_ALU.sim/sim_1/behav/xsim/ALU.vcd
$date
   Thu Feb 13 23:05:38 2025
$end

$version
  2024.2.0
  $dumpfile ("ALU.vcd") 
$end

$timescale
  1ps
$end

$scope module alu_tb $end
$var reg 4 ! op [3:0] $end
$var reg 16 " expected [15:0] $end
$var reg 16 # in1 [15:0] $end
$var reg 16 $ in2 [15:0] $end
$var reg 1 % alu_enable $end
$var wire 16 & out [15:0] $end
$var reg 1 ' clk $end
$scope module alu0 $end
$var wire 4 ( op [3:0] $end
$var wire 16 ) in1 [15:0] $end
$var wire 16 * in2 [15:0] $end
$var wire 1 + clk $end
$var wire 1 , alu_enable $end
$var reg 16 - out [15:0] $end
$upscope $end
$scope begin Block32_3 $end
$var integer 32 . i [31:0] $end
$upscope $end
$upscope $end
$enddefinitions $end

#0
$dumpvars
bx !
bx "
bx #
bx $
1%
bz &
1'
bx (
bx )
bx *
1+
1,
bz -
bx .
$end

#5000
0'
0+

#10000
1'
1+

#15000
0'
0+

#20000
1'
1+

#25000
0'
0+

#30000
1'
1+

#35000
0'
0+

#40000
1'
1+

#45000
0'
0+

#50000
1'
1+
b0 .

#55000
0'
0+

#60000
b0 !
b1100 "
b101 #
b111 $
b1100 &
1'
b0 (
b101 )
b111 *
1+
b1100 -
b1 .

#65000
0'
0+

#70000
b1 !
b1011 "
b1111 #
b100 $
b1011 &
1'
b1 (
b1111 )
b100 *
1+
b1011 -
b10 .

#75000
0'
0+

#80000
b10 !
b100100 "
b100 #
b1001 $
b100100 &
1'
b10 (
b100 )
b1001 *
1+
b100100 -
b11 .

#85000
0'
0+

#90000
b11 !
b1 "
b101 #
b111 $
b1 &
1'
b11 (
b101 )
b111 *
1+
b1 -
b100 .

#95000
0'
0+

#100000
b100 !
b1000 "
b1001 #
b1100 $
b1000 &
1'
b100 (
b1001 )
b1100 *
1+
b1000 -
b101 .

#105000
0'
0+

#110000
b101 !
b1101 "
b1101 &
1'
b101 (
1+
b1101 -
b110 .

#115000
0'
0+

#120000
b110 !
b101 "
b101 &
1'
b110 (
1+
b101 -
b111 .

#125000
0'
0+

#130000
b111 !
b101000 "
b101 #
b11 $
b101000 &
1'
b111 (
b101 )
b11 *
1+
b101000 -
b1000 .

#135000
0'
0+

#140000
b1000 !
b10 "
b1000 #
b10 $
b10 &
1'
b1000 (
b1000 )
b10 *
1+
b10 -
b1001 .

